cdk_lambda_extensions/__init__.py
cdk_lambda_extensions/py.typed
cdk_lambda_extensions/_jsii/__init__.py
cdk_lambda_extensions/_jsii/cdk-lambda-extensions@0.1.279.jsii.tgz
cdk_lambda_extensions-0.1.279.dist-info/LICENSE
cdk_lambda_extensions-0.1.279.dist-info/METADATA
cdk_lambda_extensions-0.1.279.dist-info/WHEEL
cdk_lambda_extensions-0.1.279.dist-info/top_level.txt
cdk_lambda_extensions-0.1.279.dist-info/RECORD
