Metadata-Version: 2.1
Name: cdk-lambda-extensions
Version: 0.1.279
Summary: AWS CDK construct library that allows you to add any AWS Lambda extensions to the Lambda functions
Home-page: https://github.com/pahud/cdk-lambda-extensions.git
Author: Pahud Hsieh<pahudnet@gmail.com>
License: Apache-2.0
Project-URL: Source, https://github.com/pahud/cdk-lambda-extensions.git
Platform: UNKNOWN
Classifier: Intended Audience :: Developers
Classifier: Operating System :: OS Independent
Classifier: Programming Language :: JavaScript
Classifier: Programming Language :: Python :: 3 :: Only
Classifier: Programming Language :: Python :: 3.6
Classifier: Programming Language :: Python :: 3.7
Classifier: Programming Language :: Python :: 3.8
Classifier: Programming Language :: Python :: 3.9
Classifier: Typing :: Typed
Classifier: Development Status :: 5 - Production/Stable
Classifier: License :: OSI Approved
Requires-Python: >=3.6
License-File: LICENSE
Requires-Dist: aws-cdk.aws-lambda (<2.0.0,>=1.73.0)
Requires-Dist: aws-cdk.aws-s3 (<2.0.0,>=1.73.0)
Requires-Dist: aws-cdk.core (<2.0.0,>=1.73.0)
Requires-Dist: constructs (<4.0.0,>=3.2.27)
Requires-Dist: jsii (<2.0.0,>=1.46.0)
Requires-Dist: publication (>=0.0.3)
